{"config":{"output_file":null,"full_docs":false,"pub_only":false,"reachable_only":false,"distro_crate":false,"signatures":false,"borrow_data":false},"version":"0.19.0","compilation":{"directory":"c:\\Users\\rahul.damani\\Downloads\\code\\rust\\leetcode\\max_product_subarray_152","program":"C:\\Users\\rahul.damani\\.rustup\\toolchains\\stable-x86_64-pc-windows-msvc\\bin\\rls.exe","arguments":[],"output":"c:\\Users\\rahul.damani\\Downloads\\code\\rust\\leetcode\\max_product_subarray_152\\target\\rls\\debug\\deps\\libmax_product_subarray_152-3d6a2e766e27148a.rmeta"},"prelude":{"crate_id":{"name":"max_product_subarray_152","disambiguator":[6986959886424183360,17644327806208958665]},"crate_root":"src","external_crates":[{"file_name":"c:\\Users\\rahul.damani\\Downloads\\code\\rust\\leetcode\\max_product_subarray_152\\src\\main.rs","num":1,"id":{"name":"std","disambiguator":[14664243863007151186,13029296787848565560]}},{"file_name":"c:\\Users\\rahul.damani\\Downloads\\code\\rust\\leetcode\\max_product_subarray_152\\src\\main.rs","num":2,"id":{"name":"core","disambiguator":[10973483057139175867,4092977820595504105]}},{"file_name":"c:\\Users\\rahul.damani\\Downloads\\code\\rust\\leetcode\\max_product_subarray_152\\src\\main.rs","num":3,"id":{"name":"compiler_builtins","disambiguator":[5344968526663694908,5854973613798060781]}},{"file_name":"c:\\Users\\rahul.damani\\Downloads\\code\\rust\\leetcode\\max_product_subarray_152\\src\\main.rs","num":4,"id":{"name":"rustc_std_workspace_core","disambiguator":[14551701718388451589,8584422242678588409]}},{"file_name":"c:\\Users\\rahul.damani\\Downloads\\code\\rust\\leetcode\\max_product_subarray_152\\src\\main.rs","num":5,"id":{"name":"alloc","disambiguator":[6143882857039415599,5494129795406748407]}},{"file_name":"c:\\Users\\rahul.damani\\Downloads\\code\\rust\\leetcode\\max_product_subarray_152\\src\\main.rs","num":6,"id":{"name":"libc","disambiguator":[9037026435662606504,10577775618308791929]}},{"file_name":"c:\\Users\\rahul.damani\\Downloads\\code\\rust\\leetcode\\max_product_subarray_152\\src\\main.rs","num":7,"id":{"name":"unwind","disambiguator":[15244332605556921560,15997253764330093455]}},{"file_name":"c:\\Users\\rahul.damani\\Downloads\\code\\rust\\leetcode\\max_product_subarray_152\\src\\main.rs","num":8,"id":{"name":"cfg_if","disambiguator":[496393125628069379,10121348063997143337]}},{"file_name":"c:\\Users\\rahul.damani\\Downloads\\code\\rust\\leetcode\\max_product_subarray_152\\src\\main.rs","num":9,"id":{"name":"backtrace","disambiguator":[14891368759234060001,17337422003014977783]}},{"file_name":"c:\\Users\\rahul.damani\\Downloads\\code\\rust\\leetcode\\max_product_subarray_152\\src\\main.rs","num":10,"id":{"name":"rustc_demangle","disambiguator":[9539026828135594574,18385042694178804316]}},{"file_name":"c:\\Users\\rahul.damani\\Downloads\\code\\rust\\leetcode\\max_product_subarray_152\\src\\main.rs","num":11,"id":{"name":"hashbrown","disambiguator":[5817650502020334249,13012108553651615857]}},{"file_name":"c:\\Users\\rahul.damani\\Downloads\\code\\rust\\leetcode\\max_product_subarray_152\\src\\main.rs","num":12,"id":{"name":"rustc_std_workspace_alloc","disambiguator":[12364111099303107650,4225371417860886929]}},{"file_name":"c:\\Users\\rahul.damani\\Downloads\\code\\rust\\leetcode\\max_product_subarray_152\\src\\main.rs","num":13,"id":{"name":"panic_unwind","disambiguator":[1593379990131481620,6691744023912804689]}},{"file_name":"c:\\Users\\rahul.damani\\Downloads\\code\\rust\\leetcode\\max_product_subarray_152\\src\\main.rs","num":14,"id":{"name":"test","disambiguator":[14181311558872625577,6846529764749916971]}},{"file_name":"c:\\Users\\rahul.damani\\Downloads\\code\\rust\\leetcode\\max_product_subarray_152\\src\\main.rs","num":15,"id":{"name":"getopts","disambiguator":[12091291295339420085,9650622631813797027]}},{"file_name":"c:\\Users\\rahul.damani\\Downloads\\code\\rust\\leetcode\\max_product_subarray_152\\src\\main.rs","num":16,"id":{"name":"rustc_std_workspace_std","disambiguator":[17106077737335136833,17393181171574232698]}},{"file_name":"c:\\Users\\rahul.damani\\Downloads\\code\\rust\\leetcode\\max_product_subarray_152\\src\\main.rs","num":17,"id":{"name":"unicode_width","disambiguator":[18214407977569078035,8195060735585644798]}},{"file_name":"c:\\Users\\rahul.damani\\Downloads\\code\\rust\\leetcode\\max_product_subarray_152\\src\\main.rs","num":18,"id":{"name":"term","disambiguator":[8599857728895312856,5481562573304027137]}}],"span":{"file_name":"src\\main.rs","byte_start":0,"byte_end":466,"line_start":1,"line_end":17,"column_start":1,"column_end":2}},"imports":[],"defs":[{"kind":"Mod","id":{"krate":0,"index":0},"span":{"file_name":"src\\main.rs","byte_start":0,"byte_end":466,"line_start":1,"line_end":17,"column_start":1,"column_end":2},"name":"","qualname":"::","value":"src\\main.rs","parent":null,"children":[{"krate":0,"index":1},{"krate":0,"index":2},{"krate":0,"index":3},{"krate":0,"index":4},{"krate":0,"index":5}],"decl_id":null,"docs":"","sig":null,"attributes":[]},{"kind":"Function","id":{"krate":0,"index":3},"span":{"file_name":"src\\main.rs","byte_start":3,"byte_end":7,"line_start":1,"line_end":1,"column_start":4,"column_end":8},"name":"main","qualname":"::main","value":"fn () -> ()","parent":null,"children":[],"decl_id":null,"docs":"","sig":null,"attributes":[{"value":"allow(dead_code)","span":{"file_name":"src\\main.rs","byte_start":0,"byte_end":0,"line_start":1,"line_end":1,"column_start":1,"column_end":1}}]},{"kind":"Local","id":{"krate":0,"index":4294967281},"span":{"file_name":"src\\main.rs","byte_start":106,"byte_end":107,"line_start":5,"line_end":5,"column_start":16,"column_end":17},"name":"v","qualname":"::max_product::v","value":"std::vec::Vec<i32>","parent":null,"children":[],"decl_id":null,"docs":"","sig":null,"attributes":[]},{"kind":"Function","id":{"krate":0,"index":4},"span":{"file_name":"src\\main.rs","byte_start":94,"byte_end":105,"line_start":5,"line_end":5,"column_start":4,"column_end":15},"name":"max_product","qualname":"::max_product","value":"fn (v: Vec<i32>) -> i32","parent":null,"children":[],"decl_id":null,"docs":"","sig":null,"attributes":[]},{"kind":"Local","id":{"krate":0,"index":4294967272},"span":{"file_name":"src\\main.rs","byte_start":140,"byte_end":152,"line_start":6,"line_end":6,"column_start":13,"column_end":25},"name":"input_vector","qualname":"input_vector$23","value":"std::vec::Vec<i32>","parent":null,"children":[],"decl_id":null,"docs":"","sig":null,"attributes":[]},{"kind":"Local","id":{"krate":0,"index":4294967266},"span":{"file_name":"src\\main.rs","byte_start":185,"byte_end":198,"line_start":7,"line_end":7,"column_start":13,"column_end":26},"name":"output_vector","qualname":"output_vector$29","value":"std::vec::Vec<&i32>","parent":null,"children":[],"decl_id":null,"docs":"","sig":null,"attributes":[]},{"kind":"Local","id":{"krate":0,"index":4294967259},"span":{"file_name":"src\\main.rs","byte_start":232,"byte_end":238,"line_start":8,"line_end":8,"column_start":13,"column_end":19},"name":"output","qualname":"output$36","value":"i32","parent":null,"children":[],"decl_id":null,"docs":"","sig":null,"attributes":[]},{"kind":"Local","id":{"krate":0,"index":4294967253},"span":{"file_name":"src\\main.rs","byte_start":256,"byte_end":257,"line_start":9,"line_end":9,"column_start":10,"column_end":11},"name":"n","qualname":"n$42","value":"usize","parent":null,"children":[],"decl_id":null,"docs":"","sig":null,"attributes":[]},{"kind":"Local","id":{"krate":0,"index":4294967252},"span":{"file_name":"src\\main.rs","byte_start":259,"byte_end":260,"line_start":9,"line_end":9,"column_start":13,"column_end":14},"name":"i","qualname":"i$43","value":"&i32","parent":null,"children":[],"decl_id":null,"docs":"","sig":null,"attributes":[]}],"impls":[],"refs":[{"kind":"Function","span":{"file_name":"src\\main.rs","byte_start":33,"byte_end":44,"line_start":2,"line_end":2,"column_start":22,"column_end":33},"ref_id":{"krate":0,"index":4}},{"kind":"Type","span":{"file_name":"src\\main.rs","byte_start":109,"byte_end":112,"line_start":5,"line_end":5,"column_start":19,"column_end":22},"ref_id":{"krate":5,"index":3846}},{"kind":"Type","span":{"file_name":"src\\main.rs","byte_start":154,"byte_end":157,"line_start":6,"line_end":6,"column_start":27,"column_end":30},"ref_id":{"krate":5,"index":3846}},{"kind":"Type","span":{"file_name":"src\\main.rs","byte_start":200,"byte_end":203,"line_start":7,"line_end":7,"column_start":28,"column_end":31},"ref_id":{"krate":5,"index":3846}},{"kind":"Variable","span":{"file_name":"src\\main.rs","byte_start":241,"byte_end":242,"line_start":8,"line_end":8,"column_start":22,"column_end":23},"ref_id":{"krate":0,"index":4294967281}},{"kind":"Function","span":{"file_name":"src\\main.rs","byte_start":274,"byte_end":283,"line_start":9,"line_end":9,"column_start":28,"column_end":37},"ref_id":{"krate":2,"index":3684}},{"kind":"Function","span":{"file_name":"src\\main.rs","byte_start":267,"byte_end":271,"line_start":9,"line_end":9,"column_start":21,"column_end":25},"ref_id":{"krate":2,"index":5828}},{"kind":"Variable","span":{"file_name":"src\\main.rs","byte_start":265,"byte_end":266,"line_start":9,"line_end":9,"column_start":19,"column_end":20},"ref_id":{"krate":0,"index":4294967281}},{"kind":"Variable","span":{"file_name":"src\\main.rs","byte_start":299,"byte_end":300,"line_start":10,"line_end":10,"column_start":12,"column_end":13},"ref_id":{"krate":0,"index":4294967253}},{"kind":"Variable","span":{"file_name":"src\\main.rs","byte_start":309,"byte_end":315,"line_start":10,"line_end":10,"column_start":22,"column_end":28},"ref_id":{"krate":0,"index":4294967259}},{"kind":"Variable","span":{"file_name":"src\\main.rs","byte_start":318,"byte_end":319,"line_start":10,"line_end":10,"column_start":31,"column_end":32},"ref_id":{"krate":0,"index":4294967252}},{"kind":"Variable","span":{"file_name":"src\\main.rs","byte_start":322,"byte_end":328,"line_start":10,"line_end":10,"column_start":35,"column_end":41},"ref_id":{"krate":0,"index":4294967259}},{"kind":"Function","span":{"file_name":"src\\main.rs","byte_start":357,"byte_end":361,"line_start":11,"line_end":11,"column_start":27,"column_end":31},"ref_id":{"krate":5,"index":3881}},{"kind":"Variable","span":{"file_name":"src\\main.rs","byte_start":343,"byte_end":356,"line_start":11,"line_end":11,"column_start":13,"column_end":26},"ref_id":{"krate":0,"index":4294967266}},{"kind":"Variable","span":{"file_name":"src\\main.rs","byte_start":362,"byte_end":363,"line_start":11,"line_end":11,"column_start":32,"column_end":33},"ref_id":{"krate":0,"index":4294967252}},{"kind":"Variable","span":{"file_name":"src\\main.rs","byte_start":395,"byte_end":407,"line_start":13,"line_end":13,"column_start":13,"column_end":25},"ref_id":{"krate":0,"index":4294967272}},{"kind":"Function","span":{"file_name":"src\\main.rs","byte_start":428,"byte_end":434,"line_start":13,"line_end":13,"column_start":46,"column_end":52},"ref_id":{"krate":5,"index":3351}},{"kind":"Variable","span":{"file_name":"src\\main.rs","byte_start":410,"byte_end":422,"line_start":13,"line_end":13,"column_start":28,"column_end":40},"ref_id":{"krate":0,"index":4294967272}},{"kind":"Variable","span":{"file_name":"src\\main.rs","byte_start":423,"byte_end":424,"line_start":13,"line_end":13,"column_start":41,"column_end":42},"ref_id":{"krate":0,"index":4294967253}},{"kind":"Variable","span":{"file_name":"src\\main.rs","byte_start":458,"byte_end":464,"line_start":16,"line_end":16,"column_start":5,"column_end":11},"ref_id":{"krate":0,"index":4294967259}}],"macro_refs":[],"relations":[]}